logical_lens
