Metadata-Version: 1.0
Name: logical-lens
Version: 0.0.1
Summary: Python library for using parametric specifications to embed domain specific knowledge in machine learning.
Home-page: https://github.com/mvcisback/LogicalLens
Author: Marcell Vazquez-Chanlatte
Author-email: marcell.vc@eecs.berkeley.edu
License: MIT
Platform: UNKNOWN
